SSLSocket/__init__.py
SSLSocket/exceptions.py
SSLSocket/utils.py
SSLSocket/cert/55dfe063.0
SSLSocket/cert/rootCA.crt
SSLSocket/cert/rootCA.key
SSLSocket/cert/rootCA.pem
SSLSocket-0.0.0.7.dist-info/METADATA
SSLSocket-0.0.0.7.dist-info/WHEEL
SSLSocket-0.0.0.7.dist-info/top_level.txt
SSLSocket-0.0.0.7.dist-info/RECORD
