Metadata-Version: 2.1
Name: SSLSocket
Version: 0.0.0.7
Summary: Add self-cert to a http website
Home-page: https://github.com/KhanhNguyen9872/SSLSocket
Download-URL: https://github.com/KhanhNguyen9872/SSLSocket
Author: KhanhNguyen9872
Author-email: KhanhNguyen9872 <khanhvuinguyenvan800983609@gmail.com>
License: BSD-3-Clause
Project-URL: Documentation, https://github.com/KhanhNguyen9872/SSLSocket#readme
Project-URL: Issue Tracker, https://github.com/KhanhNguyen9872/SSLSocket/issues
Project-URL: Source Code, https://github.com/KhanhNguyen9872/SSLSocket
Keywords: SSLSocket
Platform: any
Classifier: License :: OSI Approved :: MIT License
Requires-Python: >=3.6
Requires-Dist: pyOpenSSL
Provides-Extra: tests
Requires-Dist: pytest; extra == "tests"
Requires-Dist: pytest-cov; extra == "tests"
